{
  "project_info": {
    "project_number": "670236404549",
    "project_id": "cookingsha-57bee",
    "storage_bucket": "cookingsha-57bee.appspot.com"
  },
  "client": [
    {
      "client_info": {
        "mobilesdk_app_id": "1:670236404549:android:6d3f23e081a21354632c2c",
        "android_client_info": {
          "package_name": "com.subi.cookingshare"
        }
      },
      "oauth_client": [
        {
          "client_id": "670236404549-o82tsl1v820iqf3olsvek3b0d7dkn0t6.apps.googleusercontent.com",
          "client_type": 3
        }
      ],
      "api_key": [
        {
          "current_key": "AIzaSyCg_vpr3OupY5PD8oSb1NHvpOZ9IVFwmTY"
        }
      ],
      "services": {
        "appinvite_service": {
          "other_platform_oauth_client": [
            {
              "client_id": "670236404549-o82tsl1v820iqf3olsvek3b0d7dkn0t6.apps.googleusercontent.com",
              "client_type": 3
            }
          ]
        }
      }
    }
  ],
  "configuration_version": "1"
}